ECOv003_L2T_STARS/ECOv003_DL.py
ECOv003_L2T_STARS/ECOv003_DL.xml
ECOv003_L2T_STARS/ECOv003_L2T_STARS.xml
ECOv003_L2T_STARS/L2TSTARSConfig.py
ECOv003_L2T_STARS/L2T_STARS.py
ECOv003_L2T_STARS/Manifest.toml
ECOv003_L2T_STARS/Project.toml
ECOv003_L2T_STARS/__init__.py
ECOv003_L2T_STARS/calibrate_fine_to_coarse.py
ECOv003_L2T_STARS/cksum.py
ECOv003_L2T_STARS/constants.py
ECOv003_L2T_STARS/exceptions.py
ECOv003_L2T_STARS/generate_L2T_STARS_runconfig.py
ECOv003_L2T_STARS/generate_NDVI_coarse_image.py
ECOv003_L2T_STARS/generate_NDVI_fine_image.py
ECOv003_L2T_STARS/generate_STARS_inputs.py
ECOv003_L2T_STARS/generate_albedo_coarse_image.py
ECOv003_L2T_STARS/generate_albedo_fine_image.py
ECOv003_L2T_STARS/generate_downsampled_filename.py
ECOv003_L2T_STARS/generate_filename.py
ECOv003_L2T_STARS/generate_input_staging_directory.py
ECOv003_L2T_STARS/generate_model_state_tile_date_directory.py
ECOv003_L2T_STARS/generate_output_directory.py
ECOv003_L2T_STARS/instantiate_STARSDataFusion_jl.py
ECOv003_L2T_STARS/load_prior.py
ECOv003_L2T_STARS/login.py
ECOv003_L2T_STARS/main.py
ECOv003_L2T_STARS/prior.py
ECOv003_L2T_STARS/process_ECOSTRESS_data_fusion_distributed_bias.jl
ECOv003_L2T_STARS/process_STARS_product.py
ECOv003_L2T_STARS/process_julia_data_fusion.py
ECOv003_L2T_STARS/retrieve_STARS_sources.py
ECOv003_L2T_STARS/runconfig.py
ECOv003_L2T_STARS/version.py
ECOv003_L2T_STARS/version.txt
ECOv003_L2T_STARS/BRDF/BRDF.py
ECOv003_L2T_STARS/BRDF/SZA.py
ECOv003_L2T_STARS/BRDF/__init__.py
ECOv003_L2T_STARS/BRDF/statistical_radiative_transport.txt
ECOv003_L2T_STARS/BRDF/version.txt
ECOv003_L2T_STARS/LPDAAC/LPDAACDataPool.py
ECOv003_L2T_STARS/LPDAAC/__init__.py
ECOv003_L2T_STARS/LPDAAC/version.txt
ECOv003_L2T_STARS/VIIRS/VIIRSDataPool.py
ECOv003_L2T_STARS/VIIRS/VIIRSDownloader.py
ECOv003_L2T_STARS/VIIRS/VNP09GA.py
ECOv003_L2T_STARS/VIIRS/VNP43IA4.py
ECOv003_L2T_STARS/VIIRS/VNP43MA3.py
ECOv003_L2T_STARS/VIIRS/__init__.py
ECOv003_L2T_STARS/VIIRS/version.txt
ecov003_l2t_stars-1.10.0.dist-info/licenses/LICENSE
ecov003_l2t_stars-1.10.0.dist-info/METADATA
ecov003_l2t_stars-1.10.0.dist-info/WHEEL
ecov003_l2t_stars-1.10.0.dist-info/entry_points.txt
ecov003_l2t_stars-1.10.0.dist-info/top_level.txt
ecov003_l2t_stars-1.10.0.dist-info/RECORD
