Metadata-Version: 2.4
Name: ECOv003-L2T-STARS
Version: 1.10.0
Summary: ECOSTRESS Collection 3 JPL STARS Data Fusion Product Generating Executable (PGE)
Author-email: "Gregory H. Halverson" <gregory.h.halverson@jpl.nasa.gov>
Project-URL: Homepage, https://github.com/ECOSTRESS-Collection-3/ECOv003-L2T-STARS
Classifier: Programming Language :: Python :: 3
Classifier: Operating System :: OS Independent
Requires-Python: >=3.10
License-File: LICENSE
Requires-Dist: colored-logging
Requires-Dist: ECOv002-CMR>=1.0.4
Requires-Dist: ECOv002-granules
Requires-Dist: ECOv003-granules
Requires-Dist: ECOv003-exit-codes>=1.1.0
Requires-Dist: GEOS5FP
Requires-Dist: h5py
Requires-Dist: harmonized-landsat-sentinel>=2.0.0
Requires-Dist: matplotlib
Requires-Dist: modland
Requires-Dist: numpy
Requires-Dist: pandas
Requires-Dist: pytictoc
Requires-Dist: rasters
Requires-Dist: scikit-image
Requires-Dist: scipy
Requires-Dist: sentinel-tiles
Requires-Dist: shapely
Requires-Dist: untangle
Requires-Dist: xmltodict
Provides-Extra: dev
Requires-Dist: build; extra == "dev"
Requires-Dist: pytest>=6.0; extra == "dev"
Requires-Dist: pytest-cov; extra == "dev"
Requires-Dist: jupyter; extra == "dev"
Requires-Dist: pytest; extra == "dev"
Requires-Dist: twine; extra == "dev"
Dynamic: license-file
